evorbf/__init__.py
evorbf/core/__init__.py
evorbf/core/advanced_rbf.py
evorbf/core/base_rbf.py
evorbf/core/nia_rbf.py
evorbf/core/rbf_tuner.py
evorbf/core/standard_rbf.py
evorbf/helpers/__init__.py
evorbf/helpers/center_finder.py
evorbf/helpers/kernel.py
evorbf/helpers/metrics.py
evorbf/helpers/preprocessor.py
evorbf/helpers/scaler.py
evorbf/helpers/validator.py
evorbf-2.1.0.dist-info/licenses/LICENSE
evorbf-2.1.0.dist-info/METADATA
evorbf-2.1.0.dist-info/WHEEL
evorbf-2.1.0.dist-info/top_level.txt
evorbf-2.1.0.dist-info/RECORD
